create_flask_app/__init__.py
create_flask_app/create_flask_app.py
create_flask_app/app/.dockerignore
create_flask_app/app/.gitignore
create_flask_app/app/Dockerfile
create_flask_app/app/Makefile
create_flask_app/app/Procfile
create_flask_app/app/README.md
create_flask_app/app/app.py
create_flask_app/app/config.py
create_flask_app/app/docker-compose.yml
create_flask_app/app/models.py
create_flask_app/app/requirements.txt
create_flask_app/app/runtime.txt
create_flask_app/app/setup.py
create_flask_app/app/tox.ini
create_flask_app/app/static/css/style.css
create_flask_app/app/static/js/main.js
create_flask_app/app/static/scss/style.scss
create_flask_app/app/templates/base.html
create_flask_app/app/templates/index.html
create_flask_app/app/tests/client.py
create_flask_app/app/tests/test_app.py
create_flask_app/app/tests/__pycache__/client.cpython-38.pyc
create_flask_app/app/tests/__pycache__/test_app.cpython-38-pytest-6.0.1.pyc
new_flask_app-1.0.4.dist-info/LICENSE
new_flask_app-1.0.4.dist-info/METADATA
new_flask_app-1.0.4.dist-info/WHEEL
new_flask_app-1.0.4.dist-info/entry_points.txt
new_flask_app-1.0.4.dist-info/top_level.txt
new_flask_app-1.0.4.dist-info/RECORD
