Metadata-Version: 2.1
Name: new-flask-app
Version: 1.0.4
Summary: Autogenerate boilerplate code for a Flask app
Home-page: https://github.com/drizzleco/create-flask-app
Author: Philip Zhang
Author-email: jmslca123@gmail.com
License: MIT
Classifier: Intended Audience :: Developers
Classifier: Programming Language :: Python :: 3
Classifier: License :: OSI Approved :: MIT License
Classifier: Operating System :: OS Independent
Requires-Python: >=3.8
License-File: LICENSE
Requires-Dist: InquirerPy
Requires-Dist: jinja2
